setup.py
shortmomi/__init__.py
shortmomi/affinity_rules.py
shortmomi/connect.py
shortmomi/custom_attributes.py
shortmomi/datastores.py
shortmomi/tags.py
shortmomi/tasks.py
shortmomi/utils.py
shortmomi/views.py
shortmomi/vm.py
shortmomi.egg-info/PKG-INFO
shortmomi.egg-info/SOURCES.txt
shortmomi.egg-info/dependency_links.txt
shortmomi.egg-info/requires.txt
shortmomi.egg-info/top_level.txt