Metadata-Version: 1.0
Name: shortmomi
Version: 1.11.4
Summary: Bundle of useful functions and shortcuts for pyVmomi
Home-page: https://github.com/pschmitt/shortmomi
Author: Philipp Schmitt
Author-email: philipp@schmitt.co
License: GPL3
Platform: UNKNOWN
